pandas_gbq/__init__.py
pandas_gbq/_versions_helpers.py
pandas_gbq/auth.py
pandas_gbq/constants.py
pandas_gbq/contexts.py
pandas_gbq/environment.py
pandas_gbq/exceptions.py
pandas_gbq/features.py
pandas_gbq/gbq.py
pandas_gbq/gbq_connector.py
pandas_gbq/query.py
pandas_gbq/timestamp.py
pandas_gbq/version.py
pandas_gbq/core/__init__.py
pandas_gbq/core/pandas.py
pandas_gbq/load/__init__.py
pandas_gbq/load/core.py
pandas_gbq/schema/__init__.py
pandas_gbq/schema/bigquery.py
pandas_gbq/schema/pandas_to_bigquery.py
pandas_gbq/schema/pyarrow_to_bigquery.py
pandas_gbq-0.29.0.dist-info/AUTHORS.md
pandas_gbq-0.29.0.dist-info/LICENSE.txt
pandas_gbq-0.29.0.dist-info/METADATA
pandas_gbq-0.29.0.dist-info/WHEEL
pandas_gbq-0.29.0.dist-info/top_level.txt
pandas_gbq-0.29.0.dist-info/RECORD
