Metadata-Version: 2.1
Name: pandas-gbq
Version: 0.29.0
Summary: Google BigQuery connector for pandas
Home-page: https://github.com/googleapis/python-bigquery-pandas
Author: pandas-gbq authors
Author-email: googleapis-packages@google.com
License: BSD-3-Clause
Platform: Posix; MacOS X; Windows
Classifier: Development Status :: 4 - Beta
Classifier: Intended Audience :: Developers
Classifier: Intended Audience :: Science/Research
Classifier: Operating System :: OS Independent
Classifier: License :: OSI Approved :: BSD License
Classifier: Programming Language :: Python
Classifier: Programming Language :: Python :: 3
Classifier: Programming Language :: Python :: 3.8
Classifier: Programming Language :: Python :: 3.9
Classifier: Programming Language :: Python :: 3.10
Classifier: Programming Language :: Python :: 3.11
Classifier: Programming Language :: Python :: 3.12
Classifier: Operating System :: OS Independent
Classifier: Topic :: Internet
Classifier: Topic :: Scientific/Engineering
Requires-Python: >=3.8
License-File: LICENSE.txt
License-File: AUTHORS.md
Requires-Dist: setuptools
Requires-Dist: db-dtypes<2.0.0,>=1.0.4
Requires-Dist: numpy>=1.18.1
Requires-Dist: pandas>=1.1.4
Requires-Dist: pyarrow>=4.0.0
Requires-Dist: pydata-google-auth>=1.5.0
Requires-Dist: google-api-core<3.0.0,>=2.10.2
Requires-Dist: google-auth>=2.13.0
Requires-Dist: google-auth-oauthlib>=0.7.0
Requires-Dist: google-cloud-bigquery<4.0.0,>=3.4.2
Requires-Dist: packaging>=22.0.0
Provides-Extra: bqstorage
Requires-Dist: google-cloud-bigquery-storage<3.0.0,>=2.16.2; extra == "bqstorage"
Provides-Extra: tqdm
Requires-Dist: tqdm>=4.23.0; extra == "tqdm"
Provides-Extra: geopandas
Requires-Dist: geopandas>=0.9.0; extra == "geopandas"
Requires-Dist: Shapely>=1.8.4; extra == "geopandas"
